{
  "experiment": "H-dependence of the per-token feature count k (the ansatz's \u03b4)",
  "results": [
    {
      "model": "pythia-160m",
      "n_tokens": 3840,
      "delta_k_vs_H": 0.030344954338592925,
      "corr_H_k": 0.1840519394589138,
      "bins": [
        {
          "H_mid": 1.3511765003204346,
          "k_mean": 1227.527099609375,
          "n": 480
        },
        {
          "H_mid": 2.989558696746826,
          "k_mean": 1257.2198486328125,
          "n": 480
        },
        {
          "H_mid": 3.824625015258789,
          "k_mean": 1259.82568359375,
          "n": 480
        },
        {
          "H_mid": 4.416833877563477,
          "k_mean": 1258.25390625,
          "n": 480
        },
        {
          "H_mid": 4.901028633117676,
          "k_mean": 1249.8868408203125,
          "n": 480
        },
        {
          "H_mid": 5.353244781494141,
          "k_mean": 1253.9532470703125,
          "n": 480
        },
        {
          "H_mid": 5.901875972747803,
          "k_mean": 1268.074462890625,
          "n": 480
        },
        {
          "H_mid": 6.93333625793457,
          "k_mean": 1326.1407470703125,
          "n": 480
        }
      ]
    },
    {
      "model": "pythia-410m",
      "n_tokens": 3840,
      "delta_k_vs_H": 0.0471353604802148,
      "corr_H_k": 0.3362820910102822,
      "bins": [
        {
          "H_mid": 0.8462996482849121,
          "k_mean": 2010.991943359375,
          "n": 480
        },
        {
          "H_mid": 2.333954334259033,
          "k_mean": 2088.52783203125,
          "n": 480
        },
        {
          "H_mid": 3.204335927963257,
          "k_mean": 2105.2041015625,
          "n": 480
        },
        {
          "H_mid": 3.7798500061035156,
          "k_mean": 2117.39306640625,
          "n": 480
        },
        {
          "H_mid": 4.346286773681641,
          "k_mean": 2143.828857421875,
          "n": 480
        },
        {
          "H_mid": 4.845268249511719,
          "k_mean": 2130.724853515625,
          "n": 480
        },
        {
          "H_mid": 5.451478004455566,
          "k_mean": 2165.12548828125,
          "n": 480
        },
        {
          "H_mid": 6.513497352600098,
          "k_mean": 2268.152587890625,
          "n": 480
        }
      ]
    }
  ]
}